tinytasktree.py
tinytasktree-0.1.1.dist-info/licenses/LICENSE.txt
tinytasktree-0.1.1.dist-info/METADATA
tinytasktree-0.1.1.dist-info/WHEEL
tinytasktree-0.1.1.dist-info/top_level.txt
tinytasktree-0.1.1.dist-info/RECORD
