Metadata-Version: 2.4
Name: tinytasktree
Version: 0.1.1
Summary: A tiny async task-tree orchestrator for Python, behavior-tree inspired and LLM-ready.
Project-URL: Repository, https://github.com/orion-arm-ai/tinytasktree
Classifier: Development Status :: 3 - Alpha
Requires-Python: <3.15,>=3.13
License-File: LICENSE.txt
Requires-Dist: orjson>=3.11.5
Requires-Dist: json-repair>=0.55.0
Requires-Dist: litellm>=1.81.0
Requires-Dist: redis>=7.1.0
Requires-Dist: fastapi>=0.128.0
Requires-Dist: uvicorn>=0.29.0
Dynamic: license-file
